genworlds/__init__.py
genworlds/agents/__init__.py
genworlds/agents/abstracts/__init__.py
genworlds/agents/abstracts/action_planner.py
genworlds/agents/abstracts/agent.py
genworlds/agents/abstracts/agent_state.py
genworlds/agents/abstracts/state_manager.py
genworlds/agents/abstracts/thought.py
genworlds/agents/abstracts/thought_action.py
genworlds/agents/concrete/__init__.py
genworlds/agents/concrete/basic_assistant/__init__.py
genworlds/agents/concrete/basic_assistant/action_planner.py
genworlds/agents/concrete/basic_assistant/actions.py
genworlds/agents/concrete/basic_assistant/agent.py
genworlds/agents/concrete/basic_assistant/state_manager.py
genworlds/agents/concrete/basic_assistant/thoughts/__init__.py
genworlds/agents/concrete/basic_assistant/thoughts/action_schema_selector.py
genworlds/agents/concrete/basic_assistant/thoughts/event_filler.py
genworlds/agents/concrete/basic_assistant/utils.py
genworlds/agents/memories/__init__.py
genworlds/agents/memories/simulation_memory.py
genworlds/agents/utils/__init__.py
genworlds/agents/utils/validate_action.py
genworlds/events/__init__.py
genworlds/events/abstracts/__init__.py
genworlds/events/abstracts/action.py
genworlds/events/abstracts/event.py
genworlds/objects/__init__.py
genworlds/objects/abstracts/__init__.py
genworlds/objects/abstracts/object.py
genworlds/simulation/__init__.py
genworlds/simulation/simulation.py
genworlds/simulation/sockets/__init__.py
genworlds/simulation/sockets/client.py
genworlds/simulation/sockets/handlers/__init__.py
genworlds/simulation/sockets/handlers/event_handler.py
genworlds/simulation/sockets/server.py
genworlds/simulation/sockets/test_client.py
genworlds/simulation/utils/__init__.py
genworlds/simulation/utils/launch_simulation.py
genworlds/utils/__init__.py
genworlds/utils/logging_factory.py
genworlds/utils/schema_to_model.py
genworlds/utils/test_user.py
genworlds/worlds/__init__.py
genworlds/worlds/abstracts/world.py
genworlds/worlds/abstracts/world_entity.py
genworlds-0.0.18.dist-info/LICENSE
genworlds-0.0.18.dist-info/METADATA
genworlds-0.0.18.dist-info/WHEEL
genworlds-0.0.18.dist-info/RECORD
