Metadata-Version: 2.1
Name: genworlds
Version: 0.0.18
Summary: GenWorlds by YeagerAI: Pioneering AI-based simulations based on collaborative autonomous agents.
Requires-Python: >=3.10.0,<3.12
Classifier: Programming Language :: Python :: 3
Classifier: Programming Language :: Python :: 3.10
Classifier: Programming Language :: Python :: 3.11
Requires-Dist: click (==8.1.3)
Requires-Dist: colorama (==0.4.6)
Requires-Dist: colorlog (==6.7.0)
Requires-Dist: fastapi (==0.88.0)
Requires-Dist: fastjsonschema (==2.16.3)
Requires-Dist: jsonschema (==4.17.3)
Requires-Dist: langchain (==0.0.335)
Requires-Dist: openai (==0.28.0)
Requires-Dist: prompt-toolkit (==3.0.38)
Requires-Dist: pydantic (==1.10.7)
Requires-Dist: python-dotenv (==1.0.0)
Requires-Dist: qdrant-client (==1.2.0)
Requires-Dist: threadpoolctl (==3.1.0)
Requires-Dist: tiktoken (==0.4.0)
Requires-Dist: uvicorn (==0.21.1)
Requires-Dist: websocket-client (==1.5.1)
Requires-Dist: websockets (==11.0.3)
